compyre/__init__.py
compyre/_availability.py
compyre/_default.py
compyre/_version.py
compyre/alias.py
compyre/api.py
compyre/builtin/__init__.py
compyre/builtin/_numpy.py
compyre/builtin/_pandas.py
compyre/builtin/_pydantic.py
compyre/builtin/_stdlib.py
compyre/builtin/_torch.py
compyre/builtin/_utils.py
compyre/builtin/equal_fns.py
compyre/builtin/unpack_fns.py
compyre-0.1.0.dist-info/licenses/LICENSE
compyre-0.1.0.dist-info/METADATA
compyre-0.1.0.dist-info/WHEEL
compyre-0.1.0.dist-info/top_level.txt
compyre-0.1.0.dist-info/RECORD
