Metadata-Version: 2.4
Name: compyre
Version: 0.1.0
Summary: Fully configurable unpacking and comparison logic for arbitrary objects
Author-email: Philip Meier <github.pmeier@posteo.de>
License-Expression: BSD-3-Clause
Project-URL: Repository, https://github.com/pmeier/compyre
Project-URL: Documentation, https://compyre.readthedocs.io/en/stable/
Classifier: Development Status :: 4 - Beta
Classifier: Programming Language :: Python :: 3.11
Classifier: Programming Language :: Python :: 3.12
Classifier: Programming Language :: Python :: 3.13
Requires-Python: >=3.11
License-File: LICENSE
Requires-Dist: packaging
Dynamic: license-file
